libcontractvm/ConsensusManager.py
libcontractvm/DappManager.py
libcontractvm/Log.py
libcontractvm/Wallet.py
libcontractvm/WalletChainSo.py
libcontractvm/WalletExplorer.py
libcontractvm/WalletNode.py
libcontractvm/__init__.py
libcontractvm-0.6.9.4.dist-info/DESCRIPTION.rst
libcontractvm-0.6.9.4.dist-info/METADATA
libcontractvm-0.6.9.4.dist-info/RECORD
libcontractvm-0.6.9.4.dist-info/WHEEL
libcontractvm-0.6.9.4.dist-info/metadata.json
libcontractvm-0.6.9.4.dist-info/top_level.txt
