Metadata-Version: 2.0
Name: libcontractvm
Version: 0.6.9.4
Summary: Contractvm client library
Home-page: UNKNOWN
Author: Davide Gessa
Author-email: gessadavide@gmail.com
License: UNKNOWN
Platform: UNKNOWN
Requires-Dist: base58
Requires-Dist: colorlog
Requires-Dist: json-rpc
Requires-Dist: kad.py
Requires-Dist: lxml
Requires-Dist: pycoin (==0.62)
Requires-Dist: requests
Requires-Dist: werkzeug
